setup.py
Echelon.egg-info/PKG-INFO
Echelon.egg-info/SOURCES.txt
Echelon.egg-info/dependency_links.txt
Echelon.egg-info/not-zip-safe
Echelon.egg-info/requires.txt
Echelon.egg-info/top_level.txt
echelon/__init__.py
echelon/admin.py
echelon/conf.py
echelon/context_processors.py
echelon/forms.py
echelon/models.py
echelon/urls.py
echelon/views.py
echelon/migrations/0001_initial.py
echelon/migrations/__init__.py
echelon/templatetags/__init__.py
echelon/templatetags/echelon_helpers.py
example_project/__init__.py
example_project/manage.py
example_project/settings.py
example_project/urls.py