Metadata-Version: 1.0
Name: Echelon
Version: 0.1.0
Summary: A tiny cms built with Django
Home-page: http://github.com/disqus/echelon
Author: DISQUS
Author-email: opensource@disqus.com
License: UNKNOWN
Platform: UNKNOWN
Classifier: Framework :: Django
Classifier: Intended Audience :: Developers
Classifier: Intended Audience :: End Users/Desktop
Classifier: Operating System :: OS Independent
Classifier: Topic :: Internet :: WWW/HTTP :: Site Management
